galenpy/__init__.py
galenpy/exception.py
galenpy/galen_api.py
galenpy/galen_report.py
galenpy/galen_webdriver.py
galenpy/remote_service_lifecycle.py
galenpy/remote_service_logging.py
galenpy/thrift_client.py
galenpy/pythrift/__init__.py
galenpy/pythrift/constants.py
galenpy/pythrift/GalenApiRemoteService-remote
galenpy/pythrift/GalenApiRemoteService.py
galenpy/pythrift/ttypes.py
galenpy/service/galen-api-server.jar
galenpy/utils/__init__.py
galenpy/utils/logger.py
galenpy/utils/logging.config
galenpy/utils/specs.py
galenpy-0.1.7.dist-info/DESCRIPTION.rst
galenpy-0.1.7.dist-info/METADATA
galenpy-0.1.7.dist-info/metadata.json
galenpy-0.1.7.dist-info/pbr.json
galenpy-0.1.7.dist-info/RECORD
galenpy-0.1.7.dist-info/top_level.txt
galenpy-0.1.7.dist-info/WHEEL
