Metadata-Version: 2.0
Name: galenpy
Version: 0.1.7
Summary: Porting of the Galen Framework API to Python
Home-page: https://github.com/valermor/galen-api-ports
Author: valerio morsella
Author-email: valerio.morsella@skyscanner.net
License: Apache License 2.0
Platform: UNKNOWN
Requires-Dist: selenium (>=2.44.0)
Requires-Dist: thrift
Requires-Dist: mock
